pgscatalog/core/__init__.py
pgscatalog/core/cli/__init__.py
pgscatalog/core/cli/download_cli.py
pgscatalog/core/cli/format.py
pgscatalog/core/cli/format_cli.py
pgscatalog/core/cli/relabel_cli.py
pgscatalog/core/lib/__init__.py
pgscatalog/core/lib/_config.py
pgscatalog/core/lib/_download.py
pgscatalog/core/lib/_normalise.py
pgscatalog/core/lib/_relabel.py
pgscatalog/core/lib/_sortpaths.py
pgscatalog/core/lib/catalogapi.py
pgscatalog/core/lib/effecttype.py
pgscatalog/core/lib/genomebuild.py
pgscatalog/core/lib/models.py
pgscatalog/core/lib/pgsexceptions.py
pgscatalog/core/lib/scorefiles.py
pgscatalog_core-1.0.1.dist-info/licenses/LICENSE
pgscatalog_core-1.0.1.dist-info/METADATA
pgscatalog_core-1.0.1.dist-info/WHEEL
pgscatalog_core-1.0.1.dist-info/entry_points.txt
pgscatalog_core-1.0.1.dist-info/top_level.txt
pgscatalog_core-1.0.1.dist-info/RECORD
