Metadata-Version: 2.4
Name: pgscatalog.core
Version: 1.0.1
Summary: Core tools for working with polygenic scores (PGS) and the PGS Catalog
Author-email: Benjamin Wingfield <bwingfield@ebi.ac.uk>, Samuel Lambert <sl925@medschl.cam.ac.uk>, Laurent Gil <lg10@sanger.ac.uk>, Florent Yvon <fy279@cam.ac.uk>
License-Expression: Apache-2.0
Classifier: Development Status :: 5 - Production/Stable
Classifier: Environment :: Console
Classifier: Intended Audience :: Science/Research
Classifier: Programming Language :: Python
Classifier: Programming Language :: Python :: 3
Classifier: Programming Language :: Python :: 3.10
Classifier: Programming Language :: Python :: 3.11
Classifier: Programming Language :: Python :: 3.12
Requires-Python: >=3.10
License-File: LICENSE
Requires-Dist: httpx>=0.28.1
Requires-Dist: natsort>=8.4.0
Requires-Dist: pydantic>=2.10.6
Requires-Dist: pyliftover>=0.4.1
Requires-Dist: tenacity>=9.0.0
Requires-Dist: tqdm>=4.67.1
Requires-Dist: xopen[zstd]>=2.0.2
Dynamic: license-file
